CHANGES.txt
CONTRIBUTORS.txt
README.txt
setup.py
tox.ini
src/rebecca/__init__.py
src/rebecca.todict_bpmappers.egg-info/PKG-INFO
src/rebecca.todict_bpmappers.egg-info/SOURCES.txt
src/rebecca.todict_bpmappers.egg-info/dependency_links.txt
src/rebecca.todict_bpmappers.egg-info/entry_points.txt
src/rebecca.todict_bpmappers.egg-info/namespace_packages.txt
src/rebecca.todict_bpmappers.egg-info/not-zip-safe
src/rebecca.todict_bpmappers.egg-info/requires.txt
src/rebecca.todict_bpmappers.egg-info/top_level.txt
src/rebecca/todict_bpmappers/__init__.py
tests/dummy.py
tests/test_it.py